<?xml version="1.0" encoding="utf-8" ?>
<dwsync>
<file name="_LGPL.txt" server="C:/SERVER/wamp/www/mundialis.com.br/app/" local="130817401848740000" remote="130817401840000000" Dst="1" />
<file name="_lisez_moi.txt" server="C:/SERVER/wamp/www/mundialis.com.br/app/" local="130817401848896000" remote="130817401840000000" Dst="1" />
<file name="image.php" server="C:/SERVER/wamp/www/mundialis.com.br/app/" local="130817401848116000" remote="130817401840000000" Dst="1" />
<file name="index.php" server="C:/SERVER/wamp/www/mundialis.com.br/app/" local="130817401848272000" remote="130817401840000000" Dst="1" />
<file name="qrcode.class.php" server="C:/SERVER/wamp/www/mundialis.com.br/app/" local="130817401848584000" remote="130817401840000000" Dst="1" />
<file name="qrcode.class.php" server="C:/SERVER/wamp/www/skins/" local="130817401848584000" remote="130817401840000000" Dst="1" />
<file name="image.php" server="C:/SERVER/wamp/www/skins/" local="130817401848116000" remote="130817401840000000" Dst="1" />
<file name="index.php" server="C:/SERVER/wamp/www/skins/" local="130817401848272000" remote="130817401840000000" Dst="1" />
<file name="_LGPL.txt" server="C:/SERVER/wamp/www/skins/" local="130817401848740000" remote="130817401840000000" Dst="1" />
<file name="_lisez_moi.txt" server="C:/SERVER/wamp/www/skins/" local="130817401848896000" remote="130817401840000000" Dst="1" />
</dwsync>